flask_slack/__init__.py
flask_slack/exceptions.py
flask_slack/slack.py
flask_slack/utils.py
Flask_Slack-0.1.5.dist-info/DESCRIPTION.rst
Flask_Slack-0.1.5.dist-info/METADATA
Flask_Slack-0.1.5.dist-info/metadata.json
Flask_Slack-0.1.5.dist-info/RECORD
Flask_Slack-0.1.5.dist-info/top_level.txt
Flask_Slack-0.1.5.dist-info/WHEEL
